nwavclauncher/__init__.py
nwavclauncher/__main__.py
nwavclauncher/utils.py
nwavclauncher-0.1.0.dist-info/WHEEL
nwavclauncher-0.1.0.dist-info/METADATA
nwavclauncher-0.1.0.dist-info/RECORD
