Metadata-Version: 2.1
Name: nwavclauncher
Version: 0.1.0
Summary: 
Author: NativeWaves
Author-email: contact@nativewaves.com
Requires-Python: >=3.7,<4.0
Classifier: Programming Language :: Python :: 3
Classifier: Programming Language :: Python :: 3.7
Classifier: Programming Language :: Python :: 3.8
Requires-Dist: requests
